{
  "festivalId": "east-district-fun-summer-2026",
  "name": "混東區 潮 FUN 夏日趴 2026",
  "startTime": "2026-07-25T15:05:00+08:00",
  "endTime": "2026-07-26T20:15:00+08:00",
  "theme": {
    "primary": "",
    "secondary": "",
    "generated": false
  },
  "location": {
    "name": "台北東區大安路一段封街",
    "address": "台北東區大安路一段封街",
    "latitude": 0,
    "longitude": 0
  },
  "stages": [
    {
      "id": "main",
      "name": "舞台",
      "performances": [
        {
          "artist": "TDC偶像表演學院 開場演出",
          "start": "2026-07-25T15:05:00+08:00",
          "end": "2026-07-25T15:10:00+08:00"
        },
        {
          "artist": "記者會啟動儀式",
          "start": "2026-07-25T15:10:00+08:00",
          "end": "2026-07-25T15:40:00+08:00"
        },
        {
          "artist": "TDC偶像表演學院 演出",
          "start": "2026-07-25T15:40:00+08:00",
          "end": "2026-07-25T15:50:00+08:00"
        },
        {
          "artist": "火星混蛋",
          "start": "2026-07-25T16:10:00+08:00",
          "end": "2026-07-25T16:50:00+08:00"
        },
        {
          "artist": "核果人 NUTS",
          "start": "2026-07-25T17:20:00+08:00",
          "end": "2026-07-25T18:00:00+08:00"
        },
        {
          "artist": "Crispy 脆樂團",
          "start": "2026-07-25T18:30:00+08:00",
          "end": "2026-07-25T19:00:00+08:00"
        },
        {
          "artist": "怕胖團",
          "start": "2026-07-25T19:30:00+08:00",
          "end": "2026-07-25T20:10:00+08:00"
        },
        {
          "artist": "DJ DZRT FRST 華語金曲派對",
          "start": "2026-07-25T20:15:00+08:00",
          "end": "2026-07-25T21:10:00+08:00"
        },
        {
          "artist": "DJ 濱崎 K POP派對",
          "start": "2026-07-26T14:10:00+08:00",
          "end": "2026-07-26T14:30:00+08:00"
        },
        {
          "artist": "DragonBeauties 新光人壽小龍女",
          "start": "2026-07-26T14:35:00+08:00",
          "end": "2026-07-26T14:40:00+08:00"
        },
        {
          "artist": "SONNIE 桑尼",
          "start": "2026-07-26T15:00:00+08:00",
          "end": "2026-07-26T15:40:00+08:00"
        },
        {
          "artist": "沉默紳士",
          "start": "2026-07-26T16:10:00+08:00",
          "end": "2026-07-26T16:50:00+08:00"
        },
        {
          "artist": "甜約翰",
          "start": "2026-07-26T17:20:00+08:00",
          "end": "2026-07-26T18:00:00+08:00"
        },
        {
          "artist": "美秀集團",
          "start": "2026-07-26T18:30:00+08:00",
          "end": "2026-07-26T19:10:00+08:00"
        },
        {
          "artist": "DJ GOLD 華語金曲派對",
          "start": "2026-07-26T19:15:00+08:00",
          "end": "2026-07-26T20:15:00+08:00"
        }
      ]
    }
  ],
  "map": {
    "image": "",
    "notes": []
  },
  "contributors": []
}
